django_ssl_slapper-1.2.dist-info/DESCRIPTION.rst
django_ssl_slapper-1.2.dist-info/METADATA
django_ssl_slapper-1.2.dist-info/RECORD
django_ssl_slapper-1.2.dist-info/WHEEL
django_ssl_slapper-1.2.dist-info/metadata.json
django_ssl_slapper-1.2.dist-info/top_level.txt
ssl_slapper/__init__.py
ssl_slapper/middleware.py
