Metadata-Version: 2.0
Name: django-ssl-slapper
Version: 1.2
Summary: A middleware that secures URLS.
Home-page: https://bitbucket.org/queenorych/django-ssl-slapper
Author: Mike Dobbs
Author-email: mike.j.dobbs@gmail.com
License: UNKNOWN
Platform: UNKNOWN
Classifier: Environment :: Web Environment
Classifier: License :: OSI Approved :: BSD License
Classifier: Framework :: Django
Classifier: Programming Language :: Python
